{
  "id": 76702,
  "slug": "vivo-y32t-2022-4g-standard-edition-dual-sim-td-lte-cn-64gb-v2168a",
  "base_model_slug": "vivo",
  "name": "vivo Y32t 2022 4G Standard Edition Dual SIM TD-LTE CN 64GB V2168A",
  "brand": {
    "id": 52,
    "slug": "vivo",
    "name": "vivo",
    "country": "CN",
    "url": "/v1/brands/vivo"
  },
  "soc": {
    "id": 1134,
    "slug": "mediatek-helio-p70-mt6771wt",
    "name": "MediaTek Helio P70 MT6771WT",
    "manufacturer": {
      "slug": "mediatek",
      "name": "MediaTek",
      "url": "/v1/brands/mediatek"
    },
    "process_nm": 12.0,
    "gpu_name": "ARM Mali-G72MP3",
    "url": "/v1/socs/mediatek-helio-p70-mt6771wt"
  },
  "release_date": "2022-08-01",
  "msrp_usd": null,
  "ram_gb": 4,
  "storage_options_gb": [
    64
  ],
  "variant": {
    "region": "us",
    "source_category": "smartphone-variant-import",
    "source_slug": "vivo-y32t-2022-4g-standard-edition-dual-sim-td-lte-cn-64gb-v2168a",
    "memory": {
      "ram_gb": 4,
      "storage_gb": 64
    },
    "network": {
      "cellular": "4G LTE"
    },
    "sim": "dual SIM",
    "model_numbers": [
      "Y32T-2022-4G-STANDARD-EDITION-DUAL-SIM-TD-LTE-CN-64GB-V2168A"
    ]
  },
  "display": {
    "size_inch": 6.51,
    "resolution": "720x1600",
    "type": "Color IPS TFT LCD display",
    "ppi": 270
  },
  "cameras": [
    {
      "type": "main",
      "mp": 13.0
    },
    {
      "type": "selfie",
      "mp": 8.0
    }
  ],
  "battery_mah": 5000,
  "charging_wired_w": null,
  "charging_wireless_w": null,
  "weight_g": 179.0,
  "dimensions": {},
  "ip_rating": null,
  "os": "Android",
  "os_version": null,
  "connectivity": {
    "bluetooth": "Bluetooth 4.2",
    "usb": "USB Micro-AB"
  },
  "image_url": null,
  "images": [],
  "score": {
    "algorithm_version": "2.0.0",
    "overall": 27.5,
    "performance": null,
    "camera": 6.6,
    "battery": 39.2,
    "display": 36.7,
    "value": null,
    "perf": {
      "index": null,
      "percentile": null,
      "tier": null,
      "era": "2022-2023",
      "source": null
    }
  },
  "verified": false,
  "source_urls": [
    "https://www.kaggle.com/datasets/sady36/mobile-phones-specs"
  ],
  "created_at": "2026-06-24T08:54:22.687606",
  "updated_at": "2026-06-24T08:54:22.687618"
}
