{
  "slug": "samsung-sm-j530y-galaxy-j5-pro-2017-td-lte-32gb-samsung-j530",
  "name": "Samsung SM-J530Y Galaxy J5 Pro 2017 TD-LTE 32GB (Samsung J530)",
  "brand": "samsung",
  "soc": "samsung-exynos-7-octa-7870",
  "release_date": "2017-07-01",
  "ram_gb": 3,
  "battery_mah": 3000,
  "weight_g": 160.0,
  "os": "Android",
  "verified": true,
  "source_urls": [
    "https://phonedb.net/index.php?m=device&id=18586"
  ],
  "storage_options_gb": [
    32
  ],
  "display": {
    "size_inch": 5.19,
    "resolution": "720x1280",
    "type": "AM-OLED display",
    "ppi": 283
  },
  "market_regions": "Australia",
  "market_countries": "Australia , NZ"
}
