{
  "slug": "samsung-sm-j106m-galaxy-j1-mini-prime-2017-4g-lte-samsung-j106",
  "name": "Samsung SM-J106M Galaxy J1 Mini Prime 2017 4G LTE (Samsung J106)",
  "brand": "samsung",
  "soc": "spreadtrum-sc9830i",
  "release_date": "2017-03-01",
  "ram_gb": 1,
  "battery_mah": 1500,
  "weight_g": 126.0,
  "os": "Android",
  "verified": false,
  "source_urls": [
    "https://phonedb.net/index.php?m=device&id=19999"
  ],
  "storage_options_gb": [
    8
  ],
  "display": {
    "size_inch": 3.97,
    "resolution": "480x800",
    "type": "Color TN-TFT LCD display",
    "ppi": 235
  },
  "market_regions": "Central America , South America",
  "market_countries": "Argentina , Bolivia , Chile , Costa Rica , Ecuador , Panama , Paraguay , Peru"
}
