{
  "id": 89617,
  "slug": "zte-nubia-red-magic-7s-pro-5g-top-edition-global-dual-sim-td-lte-51-6981e044-sady36-bulgaria-18gb-512gb",
  "base_model_slug": "nubia-red-magic-7s-pro-5g-top-edition-global-dual-sim-td-lte-51-6981e044",
  "name": "Nubia Red Magic 7S Pro 5G Top Edition Global Dual SIM TD-LTE 512GB NX709S",
  "brand": {
    "id": 55,
    "slug": "zte",
    "name": "ZTE",
    "country": "CN",
    "url": "/v1/brands/zte"
  },
  "soc": {
    "id": 1410,
    "slug": "qualcomm-snapdragon",
    "name": "Qualcomm Snapdragon",
    "manufacturer": {
      "slug": "qualcomm",
      "name": "Qualcomm",
      "url": "/v1/brands/qualcomm"
    },
    "process_nm": 45.0,
    "gpu_name": "Unknown mobile GPU",
    "url": "/v1/socs/qualcomm-snapdragon"
  },
  "release_date": "2022-08-09",
  "msrp_usd": null,
  "ram_gb": 18,
  "storage_options_gb": [
    512
  ],
  "variant": {
    "region": "bulgaria",
    "market_country": "Bulgaria",
    "source_dataset": "sady36/mobile-phones-specs",
    "source_key": "sady36/mobile-phones-specs:6771:bulgaria",
    "memory": {
      "ram_gb": 18,
      "storage_gb": 512
    },
    "market_regions": "Asia , Australia , Eastern Europe , Europe , Middle East , North America , South America , Southeast Asia , Western Europe"
  },
  "display": {
    "size_inch": 6.8,
    "resolution": "1080x2400",
    "type": "AM-OLED display",
    "refresh_hz": 120
  },
  "cameras": [
    {
      "type": "main",
      "mp": 64.4
    },
    {
      "type": "selfie",
      "mp": 15.9
    }
  ],
  "battery_mah": 5000,
  "charging_wired_w": null,
  "charging_wireless_w": null,
  "weight_g": 235.0,
  "dimensions": {},
  "ip_rating": null,
  "os": "Google Android 12 (S)",
  "os_version": null,
  "connectivity": {
    "bluetooth": "Bluetooth 5.2"
  },
  "image_url": null,
  "images": [],
  "score": {
    "algorithm_version": "2.0.0",
    "overall": 36.7,
    "performance": null,
    "camera": 22.6,
    "battery": 35.0,
    "display": 52.5,
    "value": null,
    "perf": {
      "index": null,
      "percentile": null,
      "tier": null,
      "era": "2022-2023",
      "source": null
    }
  },
  "verified": false,
  "source_urls": [
    "https://www.kaggle.com/datasets/sady36/mobile-phones-specs"
  ],
  "created_at": "2026-06-24T08:54:27.485876",
  "updated_at": "2026-06-24T08:54:27.485889"
}
