{
  "slug": "radeon-r9-m290x-mac-edition",
  "name": "Radeon R9 M290X Mac Edition",
  "manufacturer": "amd",
  "architecture": "GCN 1.0",
  "release_date": "2014-11-23",
  "cuda_cores": 1024,
  "stream_processors": 1024,
  "memory_gb": 2.0,
  "memory_type": "GDDR5",
  "memory_bus_bit": 256,
  "memory_bandwidth_gbps": 174.7,
  "base_clock_mhz": 850,
  "boost_clock_mhz": 975,
  "tdp_w": 80,
  "pcie_version": "PCIe 3.0 x16",
  "fp32_tflops": 1.997,
  "verified": false,
  "source_urls": [
    "https://www.kaggle.com/datasets/ellimaaac/gpus-specs-from-1986-to-2026"
  ]
}
