{
  "slug": "energizer-energy-s500e-beridzeg45-4632-1gb",
  "base_model_slug": "energy-s500e",
  "name": "Energizer Energy S500E",
  "brand": "energizer",
  "release_date": "2017-01-01",
  "ram_gb": 1,
  "battery_mah": 2000,
  "weight_g": 167.0,
  "os": "Android",
  "verified": false,
  "source_urls": [
    "https://www.gsmarena.com/energizer_energy_s500e-8977.php"
  ],
  "variant": {
    "region": "global",
    "source_dataset": "beridzeg45/gsmarena-smartphones",
    "source_key": "beridzeg45/gsmarena-smartphones:4632"
  },
  "soc": "mediatek-mt6580",
  "display": {
    "size_inch": 5.0,
    "resolution": "480x854",
    "type": "TN TFT"
  },
  "cameras": [
    {
      "type": "main",
      "mp": 5.0
    },
    {
      "type": "selfie",
      "mp": 2.0
    }
  ]
}
