{
  "slug": "lg-g5-aitoolbuzz-4948-4gb-32gb-4g-lte",
  "base_model_slug": "g5",
  "name": "LG G5",
  "brand": "lg",
  "release_date": "2016-02-01",
  "ram_gb": 4,
  "battery_mah": 2800,
  "weight_g": 159.0,
  "os": "Android 6.0.1, up to Android 8.0, LG UX 5 UI",
  "verified": false,
  "source_urls": [
    "https://aitoolbuzz.com/mobiles/lg-g5"
  ],
  "variant": {
    "region": "global",
    "source_dataset": "devadigax/awesome-mobiles-database-by-aitoolbuzz-com",
    "source_key": "devadigax/awesome-mobiles-database-by-aitoolbuzz-com:4948",
    "memory": {
      "ram_gb": 4,
      "storage_gb": 32
    },
    "network": {
      "cellular": "4G LTE"
    },
    "model_numbers": [
      "H860",
      "H850",
      "F700L",
      "VS987",
      "H830",
      "H831",
      "H820",
      "H840",
      "LGLS992",
      "LGUS992",
      "F700S",
      "F700K",
      "RS988",
      "LGAS992",
      "H820PR"
    ],
    "sim": "Nano-SIMNano-SIM + Nano-SIM"
  },
  "soc": "snapdragon-820",
  "storage_options_gb": [
    32
  ],
  "display": {
    "size_inch": 5.3,
    "resolution": "1440x2560 pixels",
    "type": "IPS LCD"
  },
  "cameras": [
    {
      "type": "main",
      "raw": "16MP"
    },
    {
      "type": "selfie",
      "raw": "8 MP, f/2.0, 1/4.0\", 1.12µm"
    }
  ],
  "image_url": "https://aitoolbuzz.com/assets/agents/mobiles/lg-g5.jpg"
}
