{
  "slug": "zte-star-s2005-td-lte",
  "name": "ZTE Star S2005 TD-LTE",
  "brand": "zte",
  "soc": "qualcomm-snapdragon-800-msm8974ab-v2",
  "release_date": "2014-12-01",
  "ram_gb": 2,
  "battery_mah": 1500,
  "weight_g": 120.0,
  "os": "Android",
  "verified": false,
  "source_urls": [
    "https://phonedb.net/index.php?m=device&id=7190"
  ],
  "storage_options_gb": [
    16
  ],
  "display": {
    "size_inch": 5.0,
    "resolution": "1080x1920",
    "type": "Color TN-TFT LCD display",
    "ppi": 441
  },
  "market_countries": "China"
}
