{
  "id": 1892,
  "slug": "h100-pcie-96-gb",
  "name": "H100 PCIe 96 GB",
  "manufacturer": {
    "slug": "nvidia",
    "name": "NVIDIA",
    "url": "/v1/brands/nvidia"
  },
  "architecture": "Hopper",
  "release_date": "2023-03-21",
  "msrp_usd": null,
  "cuda_cores": 16896,
  "stream_processors": 16896,
  "rt_cores": null,
  "tensor_cores": 528,
  "memory_gb": 96.0,
  "memory_type": "HBM3",
  "memory_bus_bit": 5120,
  "memory_bandwidth_gbps": null,
  "base_clock_mhz": 1665,
  "boost_clock_mhz": 1837,
  "tdp_w": 700,
  "pcie_version": "PCIe 5.0 x16",
  "fp32_tflops": 62.08,
  "blender_score": null,
  "verified": false,
  "source_urls": [
    "https://www.kaggle.com/datasets/ellimaaac/gpus-specs-from-1986-to-2026"
  ],
  "url": "/v1/gpus/h100-pcie-96-gb"
}
