{
  "id": 11098,
  "slug": "doogee-s61-6gb-6gb-4g-lte",
  "base_model_slug": "s61",
  "name": "Doogee S61",
  "brand": {
    "id": 18,
    "slug": "doogee",
    "name": "DOOGEE",
    "country": "CN",
    "url": "/v1/brands/doogee"
  },
  "soc": {
    "id": 1192,
    "slug": "helio-g35",
    "name": "Helio G35",
    "manufacturer": {
      "slug": "mediatek",
      "name": "MediaTek",
      "url": "/v1/brands/mediatek"
    },
    "process_nm": 12.0,
    "gpu_name": "PowerVR GE8320",
    "url": "/v1/socs/helio-g35"
  },
  "release_date": "2022-07-01",
  "msrp_usd": null,
  "ram_gb": 6,
  "storage_options_gb": [
    6,
    64
  ],
  "variant": {
    "region": "global",
    "source_dataset": "devadigax/awesome-mobiles-database-by-aitoolbuzz-com",
    "memory": {
      "ram_gb": 6,
      "storage_gb": 6
    },
    "network": {
      "cellular": "4G LTE"
    },
    "sim": "Nano-SIM + Nano-SIM"
  },
  "display": {
    "size": "6.0\"",
    "resolution": "720x1440 pixels",
    "type": "IPS LCD"
  },
  "cameras": [
    {
      "type": "main",
      "raw": "20MP"
    },
    {
      "type": "selfie",
      "raw": "8 MP, f/2.0, (wide)"
    }
  ],
  "battery_mah": 5180,
  "charging_wired_w": null,
  "charging_wireless_w": null,
  "weight_g": 266.0,
  "dimensions": {},
  "ip_rating": null,
  "os": "Android 12",
  "os_version": null,
  "connectivity": {
    "wifi": "Wi-Fi 802.11 a/b/g/n/ac, dual-band",
    "bluetooth": "5.0, A2DP, LE",
    "nfc": "Yes",
    "usb": "USB Type-C 2.0, OTG"
  },
  "image_url": "https://aitoolbuzz.com/assets/agents/mobiles/doogee-s61.jpg",
  "images": [],
  "score": {
    "algorithm_version": "2.0.0",
    "overall": 28.6,
    "performance": 16.1,
    "camera": null,
    "battery": 41.0,
    "display": null,
    "value": null,
    "perf": {
      "index": 16.1,
      "percentile": 6.4,
      "tier": "E",
      "era": "2022-2023",
      "source": "geekbench"
    }
  },
  "verified": false,
  "source_urls": [
    "https://aitoolbuzz.com/mobiles/doogee-s61"
  ],
  "created_at": "2026-06-24T08:53:54.448704",
  "updated_at": "2026-06-24T08:53:54.448716"
}
