{
  "slug": "coolpad-cp12-4gb-128gb-4g-lte",
  "name": "Coolpad CP12",
  "brand": "coolpad",
  "release_date": "2023-06-15",
  "ram_gb": 4,
  "battery_mah": 4500,
  "weight_g": 190.0,
  "os": "Android v13",
  "verified": false,
  "source_urls": [
    "https://www.kaggle.com/datasets/mayankkumarpoddar/smartprix-mobiles-dataset"
  ],
  "base_model_slug": "cp12",
  "variant": {
    "region": "global",
    "source_dataset": "mayankkumarpoddar/smartprix-mobiles-dataset",
    "memory": {
      "ram_gb": 4,
      "storage_gb": 128
    },
    "network": {
      "cellular": "4G LTE"
    }
  },
  "storage_options_gb": [
    128
  ],
  "display": {
    "size": "6.52 inches, 720 x 1600 pixels",
    "resolution": "~ 269 PPI",
    "type": "Color IPS Screen (1B Colors)"
  },
  "connectivity": {
    "wifi": "Yes, with wifi-hotspot",
    "bluetooth": "Yes, v5.0",
    "nfc": "",
    "usb": "Yes, USB-C v2.0"
  },
  "raw_smartprix": {
    "Battery.Bypass Charging": "",
    "Battery.Fast Charging": "Yes, 10W",
    "Battery.Music Playback Time": "",
    "Battery.Reverse Charging": "",
    "Battery.Reverse Wireless Charging": "",
    "Battery.Size": "4500 mAh, Li-ion Battery",
    "Battery.StandBy Time": "",
    "Battery.Talk Time": "",
    "Battery.Type": "Non-Removable Battery",
    "Battery.Video Playback Time": "",
    "Battery.Wireless Charging": "",
    "Brand": "Coolpad",
    "Camera.Auto Focus": "Yes",
    "Camera.Camera Sensor": "",
    "Camera.Features": "Panorama, HDR",
    "Camera.Flash": "Yes, LED",
    "Camera.Front Camera": "5 MP<br><span class=\"dim\">Popup</span>",
    "Camera.Front Video Recording": "",
    "Camera.OIS": "",
    "Camera.Rear Camera": "13 MP (Wide Angle)<br><span class=\"dim\">AF</span><br class=\"l\">2 MP (Macro)",
    "Camera.Video Recording": "1080p @ 30 fps FHD",
    "Connectivity.3G": "Yes",
    "Connectivity.4G": "Yes",
    "Connectivity.5G": "",
    "Connectivity.5G Bands": "",
    "Connectivity.Bluetooth": "Yes, v5.0",
    "Connectivity.EDGE": "Yes",
    "Connectivity.GPRS": "Yes",
    "Connectivity.IR Blaster": "",
    "Connectivity.USB": "Yes, USB-C v2.0",
    "Connectivity.USB Features": "USB on-the-go, USB Charging",
    "Connectivity.Ultra Wideband (UWB) Support": "",
    "Connectivity.Vo5G": "",
    "Connectivity.VoLTE": "Yes, Dual Stand-By",
    "Connectivity.Wifi": "Yes, with wifi-hotspot",
    "Connectivity.Wifi Version": "",
    "Design.Bezel less": "",
    "Design.Colors": "Black, Blue, Silver",
    "Design.Design Type": "",
    "Design.Dimensions": "75.7 x 164.2 x 8.3 mm",
    "Design.Qwerty": "",
    "Design.Weight": "190 g",
    "Display.Adaptive Refresh Rate": "",
    "Display.Aspect Ratio": "20:9 ",
    "Display.Brightness": "",
    "Display.Color Gamut": "",
    "Display.Curved Display": "",
    "Display.Display Dimming": "",
    "Display.Dual Display": "",
    "Display.Features": "",
    "Display.Foldable Display": "",
    "Display.Glass Type": "",
    "Display.HDR Support": "",
    "Display.Notch": "No",
    "Display.PPI": "~ 269 PPI",
    "Display.Screen to Body Ratio": "~ 82.6%",
    "Display.Size": "6.52 inches, 720 x 1600 pixels",
    "Display.Touch": "Yes",
    "Display.Type": "Color IPS Screen (1B Colors)",
    "Extra.3.5mm Headphone Jack": "No",
    "Extra.AI Features": "",
    "Extra.Cooling System": "",
    "Extra.Dust Resistant": "",
    "Extra.Extra": "",
    "Extra.Extra Features": "",
    "Extra.Face Unlock": "Yes",
    "Extra.Fingerprint Sensor": "Yes, Side",
    "Extra.GPS": "Yes, with A-GPS, GLONASS, BDS",
    "Extra.Gaming Features": "",
    "Extra.IP Rating": "",
    "Extra.NFC": "",
    "Extra.Sensors": "accelerometer, proximity",
    "Extra.Splash Resistant": "",
    "Extra.Water Resistance": "",
    "General.Country of Origin": "",
    "General.Device Type": "Smartphone",
    "General.Dual Sim": "Yes",
    "General.In The Box": "",
    "General.Model": "CP12",
    "General.OS Updates": "",
    "General.Release Date": "June 15, 2023",
    "General.SAR": "",
    "General.Security Updates": "",
    "General.Sim Size": "Nano SIM",
    "General.Sim Type": "Dual Sim, GSM+GSM (Hybrid Slot)",
    "General.Triple Sim": "",
    "General.eSIM Support": "",
    "Last modified": "2025-11-05",
    "Memory.Card Slot": "Yes, (Hybrid Slot), upto 256 GB",
    "Memory.Expandable RAM": "",
    "Memory.Phonebook": "",
    "Memory.RAM": "4 GB",
    "Memory.RAM Type": "",
    "Memory.Storage": "128 GB",
    "Memory.Storage Type": "",
    "Multimedia.Audio Features": "",
    "Multimedia.Audio Jack Type": "",
    "Multimedia.Document Reader": "Yes",
    "Multimedia.Email": "Yes",
    "Multimedia.FM Radio": "Yes",
    "Multimedia.Music": "MP3/WAV/eAAC+/FLAC",
    "Multimedia.Speaker Type": "",
    "Multimedia.Supports": "",
    "Multimedia.Video": "MP4/H.264",
    "Name": "Coolpad CP12",
    "Performance.3DMark Score": "",
    "Performance.AnTuTu Score": "",
    "Performance.AnTuTu Storage Score": "",
    "Performance.Battery Test Result": "",
    "Performance.Camera Score": "",
    "Performance.Geekbench Score": "",
    "Performance.Speaker Score": "",
    "Price": "15999.0",
    "Price Drop": "0.0",
    "Price Drop Amount": "0",
    "Related Items": "[{\"Name\": \"Xiaomi Redmi K90 Pro Max\", \"Price\": 50990}, {\"Name\": \"Samsung Galaxy S24 Ultra\", \"Price\": 84999}, {\"Name\": \"iQOO 15\", \"Price\": 64999}, {\"Name\": \"Xiaomi Redmi K90 Pro\", \"Price\": 59990}, {\"Name\": \"iQOO Neo 11\", \"Price\": 32990}, {\"Name\": \"Red Magic 11 Pro\", \"Price\": 60990}, {\"Name\": \"OnePlus 15\", \"Price\": 64999}, {\"Name\": \"Nothing Phone 3a Lite\", \"Price\": 19999}, {\"Name\": \"Oppo Find X9 Pro 5G\", \"Price\": 74999}]",
    "Technical.Browser": "Yes, supports HTML5",
    "Technical.CPU": "1.6 GHz, Octa Core Processor",
    "Technical.Chipset": "Unisoc SC9863A",
    "Technical.Core Details": "4x2.2 GHz Cortex-A76 & 4x2.0 GHz Cortex-A55",
    "Technical.Custom UI": "",
    "Technical.Fabrication Node": "",
    "Technical.GPU": "IMG8322",
    "Technical.Java": "No",
    "Technical.NPU": "",
    "Technical.OS": "Android v13"
  },
  "soc": "unisoc-sc9863a"
}
