{
  "slug": "samsung-sgh-i437-galaxy-express",
  "name": "Samsung SGH-i437 Galaxy Express",
  "brand": "samsung",
  "soc": "qualcomm-snapdragon-s4-msm8960",
  "release_date": "2012-11-16",
  "ram_gb": 1,
  "battery_mah": 2000,
  "weight_g": 135.0,
  "os": "Android",
  "verified": false,
  "source_urls": [
    "https://phonedb.net/index.php?m=device&id=3989"
  ],
  "storage_options_gb": [
    8
  ],
  "display": {
    "size_inch": 4.49,
    "resolution": "480x800",
    "type": "AM-OLED display",
    "ppi": 208
  },
  "market_regions": "North America",
  "market_countries": "USA"
}
