{
  "slug": "meizu-18s-pro-5g-8gb-128gb-5g",
  "name": "Meizu 18s Pro 5G",
  "brand": "meizu",
  "release_date": "2021-09-22",
  "ram_gb": 8,
  "battery_mah": 4500,
  "weight_g": 189.0,
  "os": "Android v11",
  "verified": false,
  "source_urls": [
    "https://www.kaggle.com/datasets/mayankkumarpoddar/smartprix-mobiles-dataset"
  ],
  "base_model_slug": "18s-pro-5g",
  "variant": {
    "region": "global",
    "source_dataset": "mayankkumarpoddar/smartprix-mobiles-dataset",
    "memory": {
      "ram_gb": 8,
      "storage_gb": 128
    },
    "network": {
      "cellular": "5G"
    }
  },
  "storage_options_gb": [
    128
  ],
  "display": {
    "size": "6.7 inches, 1440 x 3200 pixels, 120 Hz",
    "resolution": "~ 526 PPI",
    "type": "Color Super AMOLED Screen (16M Colors)"
  },
  "connectivity": {
    "wifi": "Yes, with wifi-hotspot",
    "bluetooth": "Yes, v5.2, A2DP, LE",
    "nfc": "Yes",
    "usb": "Yes, USB-C"
  },
  "raw_smartprix": {
    "Battery.Bypass Charging": "",
    "Battery.Fast Charging": "Yes, 40W Super mCharge",
    "Battery.Music Playback Time": "",
    "Battery.Reverse Charging": "Yes, 10W",
    "Battery.Reverse Wireless Charging": "",
    "Battery.Size": "4500 mAh, Li-Po Battery",
    "Battery.StandBy Time": "",
    "Battery.Talk Time": "",
    "Battery.Type": "Non-Removable Battery",
    "Battery.Video Playback Time": "",
    "Battery.Wireless Charging": "Yes, 40W",
    "Brand": "Meizu",
    "Camera.Auto Focus": "Yes",
    "Camera.Camera Sensor": "Samsung GN1",
    "Camera.Features": "HDR, Panorama, 130° Ultra Wide Angle, DarkVision, Pure Fusion, Super Night View 4.0, ",
    "Camera.Flash": "Yes, LED",
    "Camera.Front Camera": "44 MP ƒ/2.4 (Wide Angle)<br><span class=\"dim\">Punch Hole</span>",
    "Camera.Front Video Recording": "4K, 1080p",
    "Camera.OIS": "Yes",
    "Camera.Rear Camera": "50 MP ƒ/1.9 (Wide Angle)<br class=\"l\">8 MP ƒ/2.4 (Telephoto)<br class=\"l\">32 MP ƒ/2.2 (Ultra Wide)<br class=\"l\">3 MP ƒ/1.4 (Depth Sensor)",
    "Camera.Video Recording": "8K, 4K, 1080p",
    "Connectivity.3G": "Yes",
    "Connectivity.4G": "Yes",
    "Connectivity.5G": "Yes",
    "Connectivity.5G Bands": "",
    "Connectivity.Bluetooth": "Yes, v5.2, A2DP, LE",
    "Connectivity.EDGE": "Yes",
    "Connectivity.GPRS": "Yes",
    "Connectivity.IR Blaster": "",
    "Connectivity.USB": "Yes, USB-C",
    "Connectivity.USB Features": "USB on-the-go, USB Charging",
    "Connectivity.Ultra Wideband (UWB) Support": "",
    "Connectivity.Vo5G": "",
    "Connectivity.VoLTE": "Yes",
    "Connectivity.Wifi": "Yes, with wifi-hotspot",
    "Connectivity.Wifi Version": "",
    "Design.Bezel less": "",
    "Design.Colors": "",
    "Design.Design Type": "",
    "Design.Dimensions": "73 x 162.5 x 8.1 mm",
    "Design.Qwerty": "",
    "Design.Weight": "189 g",
    "Display.Adaptive Refresh Rate": "",
    "Display.Aspect Ratio": "20:9",
    "Display.Brightness": "",
    "Display.Color Gamut": "",
    "Display.Curved Display": "",
    "Display.Display Dimming": "",
    "Display.Dual Display": "",
    "Display.Features": "HDR10+",
    "Display.Foldable Display": "",
    "Display.Glass Type": "Corning Gorilla Glass 6",
    "Display.HDR Support": "",
    "Display.Notch": "Yes, Punch Hole",
    "Display.PPI": "~ 526 PPI",
    "Display.Screen to Body Ratio": "~ 90.7%",
    "Display.Size": "6.7 inches, 1440 x 3200 pixels, 120 Hz",
    "Display.Touch": "Yes",
    "Display.Type": "Color Super AMOLED Screen (16M Colors)",
    "Extra.3.5mm Headphone Jack": "No",
    "Extra.AI Features": "",
    "Extra.Cooling System": "",
    "Extra.Dust Resistant": "",
    "Extra.Extra": "",
    "Extra.Extra Features": "",
    "Extra.Face Unlock": "Yes",
    "Extra.Fingerprint Sensor": "Yes, In Display",
    "Extra.GPS": "Yes, with dual-band A-GPS, GLONASS, BDS, GALILEO, QZSS, IRNSS",
    "Extra.Gaming Features": "",
    "Extra.IP Rating": "",
    "Extra.NFC": "Yes",
    "Extra.Sensors": "Accelerometer, Gyro, Proximity, E-compass, Distance Sensor, Pressure Sensor",
    "Extra.Splash Resistant": "",
    "Extra.Water Resistance": "",
    "General.Country of Origin": "",
    "General.Device Type": "Smartphone",
    "General.Dual Sim": "Yes",
    "General.In The Box": "",
    "General.Model": "18s Pro",
    "General.OS Updates": "",
    "General.Release Date": "September 22, 2021 ",
    "General.SAR": "",
    "General.Security Updates": "",
    "General.Sim Size": "Nano+Nano SIM",
    "General.Sim Type": "Dual Sim, GSM+GSM",
    "General.Triple Sim": "",
    "General.eSIM Support": "",
    "Last modified": "2025-09-28",
    "Memory.Card Slot": "",
    "Memory.Expandable RAM": "",
    "Memory.Phonebook": "",
    "Memory.RAM": "8 GB",
    "Memory.RAM Type": "",
    "Memory.Storage": "128 GB",
    "Memory.Storage Type": "UFS 3.1",
    "Multimedia.Audio Features": "",
    "Multimedia.Audio Jack Type": "",
    "Multimedia.Document Reader": "Yes",
    "Multimedia.Email": "Yes",
    "Multimedia.FM Radio": "No",
    "Multimedia.Music": "Yes",
    "Multimedia.Speaker Type": "",
    "Multimedia.Supports": "",
    "Multimedia.Video": "Yes",
    "Name": "Meizu 18s Pro 5G",
    "Performance.3DMark Score": "",
    "Performance.AnTuTu Score": "",
    "Performance.AnTuTu Storage Score": "",
    "Performance.Battery Test Result": "",
    "Performance.Camera Score": "",
    "Performance.Geekbench Score": "",
    "Performance.Speaker Score": "",
    "Price": "51990.0",
    "Price Drop": "0.0",
    "Price Drop Amount": "0",
    "Related Items": "[{\"Name\": \"Samsung Galaxy S24 Ultra\", \"Price\": 73999}, {\"Name\": \"OnePlus Nord CE 5 5G\", \"Price\": 23499}, {\"Name\": \"Samsung Galaxy S24 FE 5G\", \"Price\": 30000}, {\"Name\": \"Motorola Moto G86 Power 5G\", \"Price\": 16681}, {\"Name\": \"Motorola Moto G96 5G\", \"Price\": 17383}, {\"Name\": \"Xiaomi Redmi Note 14 SE 5G\", \"Price\": 13999}, {\"Name\": \"Xiaomi 17 Pro Max\", \"Price\": 74990}, {\"Name\": \"Vivo T4 Pro 5G\", \"Price\": 27445}, {\"Name\": \"Motorola Edge 60 Pro\", \"Price\": 28290}]",
    "Technical.Browser": "Yes",
    "Technical.CPU": "2.9 GHz, Octa Core Processor",
    "Technical.Chipset": "Qualcomm Snapdragon  888+",
    "Technical.Core Details": "1x2.99 GHz Kryo 680 & 3x2.42 GHz Kryo 680 & 4x1.80 GHz Kryo 680",
    "Technical.Custom UI": "",
    "Technical.Fabrication Node": "",
    "Technical.GPU": "Adreno 660",
    "Technical.Java": "No",
    "Technical.NPU": "",
    "Technical.OS": "Android v11"
  },
  "soc": "snapdragon-888-plus"
}
