{
  "slug": "oppo-realme-gt2-5g-explorer-master-top-edition-dual-sim-td-lte-cn-256gb-rmx3551-bbk-r3551",
  "name": "Oppo Realme GT2 5G Explorer Master Top Edition Dual SIM TD-LTE CN 256GB RMX3551 (BBK R3551)",
  "brand": "oppo",
  "soc": "qualcomm-snapdragon-8-gen-1-5g-sm8475",
  "release_date": "2022-07-01",
  "ram_gb": 12,
  "battery_mah": 5000,
  "weight_g": 195.0,
  "os": "Android",
  "verified": false,
  "source_urls": [
    "https://phonedb.net/index.php?m=device&id=21479"
  ],
  "storage_options_gb": [
    256
  ],
  "display": {
    "size_inch": 6.69,
    "resolution": "1080x2412",
    "type": "AM-OLED display",
    "ppi": 395
  },
  "market_regions": "Asia",
  "market_countries": "China"
}
