{
  "id": 86484,
  "slug": "xolo-black-1x-aitoolbuzz-13148-3gb",
  "base_model_slug": "black-1x",
  "name": "Black 1X",
  "brand": {
    "id": 95,
    "slug": "xolo",
    "name": "Xolo",
    "country": "IN",
    "url": "/v1/brands/xolo"
  },
  "soc": {
    "id": 1087,
    "slug": "mediatek-mt6753",
    "name": "Mediatek MT6753",
    "manufacturer": {
      "slug": "mediatek",
      "name": "MediaTek",
      "url": "/v1/brands/mediatek"
    },
    "process_nm": 28.0,
    "gpu_name": "Mali-T720MP3",
    "url": "/v1/socs/mediatek-mt6753"
  },
  "release_date": "2015-01-01",
  "msrp_usd": null,
  "ram_gb": 3,
  "storage_options_gb": [],
  "variant": {
    "region": "global",
    "source_dataset": "devadigax/awesome-mobiles-database-by-aitoolbuzz-com",
    "source_key": "devadigax/awesome-mobiles-database-by-aitoolbuzz-com:13148"
  },
  "display": {},
  "cameras": [],
  "battery_mah": 2400,
  "charging_wired_w": null,
  "charging_wireless_w": null,
  "weight_g": 150.0,
  "dimensions": {},
  "ip_rating": null,
  "os": "Android",
  "os_version": null,
  "connectivity": {},
  "image_url": "https://aitoolbuzz.com/assets/agents/mobiles/xolo-black-1x.jpg",
  "images": [],
  "score": {
    "algorithm_version": "1.0.0",
    "overall": 0.0,
    "performance": null,
    "camera": null,
    "battery": 0.0,
    "display": null,
    "value": null
  },
  "verified": false,
  "source_urls": [
    "https://aitoolbuzz.com/mobiles/xolo-black-1x"
  ],
  "created_at": "2026-06-20T19:05:31.060801",
  "updated_at": "2026-06-20T19:05:31.060801"
}
