{
  "slug": "htc-desire-826-td-lte-d826x-32gb-htc-a52",
  "name": "HTC Desire 826 TD-LTE D826x 32GB (HTC A52)",
  "brand": "htc",
  "soc": "qualcomm-snapdragon-615-msm8939",
  "release_date": "2015-02-01",
  "ram_gb": 2,
  "battery_mah": 2600,
  "weight_g": 183.0,
  "os": "Android",
  "verified": true,
  "source_urls": [
    "https://phonedb.net/index.php?m=device&id=7635"
  ],
  "storage_options_gb": [
    32
  ],
  "display": {
    "size_inch": 5.51,
    "resolution": "1080x1920",
    "type": "Color PVA TFT LCD display",
    "ppi": 400
  },
  "market_regions": "Asia",
  "market_countries": "China , Taiwan"
}
