{
  "slug": "huawei-ascend-w3-aitoolbuzz-3472-1gb-4g-lte",
  "base_model_slug": "ascend-w3",
  "name": "Huawei Ascend W3",
  "brand": "huawei",
  "release_date": "2013-01-01",
  "ram_gb": 1,
  "battery_mah": 1500,
  "weight_g": 150.0,
  "os": "Microsoft Windows Phone 8",
  "verified": false,
  "source_urls": [
    "https://aitoolbuzz.com/mobiles/huawei-ascend-w3"
  ],
  "variant": {
    "region": "global",
    "source_dataset": "devadigax/awesome-mobiles-database-by-aitoolbuzz-com",
    "source_key": "devadigax/awesome-mobiles-database-by-aitoolbuzz-com:3472",
    "network": {
      "cellular": "4G LTE"
    },
    "sim": "Micro-SIM"
  },
  "soc": "dual-core",
  "display": {
    "size_inch": 4.5,
    "resolution": "720x1280 pixels",
    "type": "IPS LCD"
  },
  "cameras": [
    {
      "type": "main",
      "raw": "8MP"
    },
    {
      "type": "selfie",
      "raw": "Yes"
    }
  ]
}
