{
  "slug": "google-pixel-5a-5g-td-lte-us-128gb-g1f8f-google-barbet",
  "name": "Google Pixel 5a 5G TD-LTE US 128GB G1F8F (Google Barbet)",
  "brand": "google",
  "soc": "qualcomm-snapdragon-765-5g-sm7250-aa",
  "release_date": "2021-08-26",
  "ram_gb": 6,
  "battery_mah": 4680,
  "weight_g": 183.0,
  "os": "Android",
  "verified": false,
  "source_urls": [
    "https://phonedb.net/index.php?m=device&id=19438"
  ],
  "storage_options_gb": [
    128
  ],
  "display": {
    "size_inch": 6.34,
    "resolution": "1080x2400",
    "type": "AM-OLED display",
    "ppi": 415
  },
  "market_regions": "Central America , North America",
  "market_countries": "Puerto Rico , USA"
}
