{
  "slug": "honor-magic-8-pro",
  "name": "Honor Magic8 Pro",
  "brand": "honor",
  "soc": "snapdragon-8-elite-gen-5",
  "release_date": "2025-10-23",
  "msrp_usd": 1499,
  "ram_gb": 16,
  "storage_options_gb": [256, 512, 1024],
  "display": {
    "size_inch": 6.71,
    "resolution": "2808x1256",
    "refresh_hz": 120,
    "type": "LTPO OLED",
    "brightness_nits": 6000,
    "ppi": 460
  },
  "cameras": [
    {"type": "main", "mp": 50, "aperture": 1.4, "ois": true},
    {"type": "ultrawide", "mp": 50, "aperture": 2.0, "ois": false},
    {"type": "telephoto", "mp": 200, "aperture": 2.6, "ois": true, "optical_zoom": 3.7},
    {"type": "selfie", "mp": 50, "aperture": 2.0}
  ],
  "battery_mah": 7100,
  "charging_wired_w": 100,
  "charging_wireless_w": 80,
  "weight_g": 224.0,
  "dimensions": {"height_mm": 162.8, "width_mm": 76.9, "depth_mm": 8.4},
  "ip_rating": "IP69",
  "os": "Android",
  "os_version": "16",
  "connectivity": {"wifi": "Wi-Fi 7", "bluetooth": "5.4", "nfc": true, "usb": "USB-C 3.2"},
  "image_url": "https://cdn.jsdelivr.net/gh/GetTechAPI/images/smartphones/honor-magic-8-pro.webp",
  "verified": false,
  "source_urls": [
    "https://www.honor.com/global/phones/honor-magic8-pro/spec/",
    "https://www.gsmarena.com/honor_magic8_pro_5g-14231.php"
  ]
}
