{
  "id": 57560,
  "slug": "samsung-sm-g3818-galaxy-win-pro",
  "base_model_slug": null,
  "name": "Samsung SM-G3818 Galaxy Win Pro",
  "brand": {
    "id": 113,
    "slug": "samsung",
    "name": "Samsung",
    "country": "KR",
    "url": "/v1/brands/samsung"
  },
  "soc": {
    "id": 984,
    "slug": "marvell-armada-pxa1088",
    "name": "Marvell ARMADA PXA1088",
    "manufacturer": {
      "slug": "marvell",
      "name": "Marvell Technology",
      "url": "/v1/brands/marvell"
    },
    "process_nm": 28.0,
    "gpu_name": "N/A",
    "url": "/v1/socs/marvell-armada-pxa1088"
  },
  "release_date": "2014-04-01",
  "msrp_usd": null,
  "ram_gb": 1,
  "storage_options_gb": [],
  "variant": {},
  "display": {
    "size_inch": 4.5,
    "resolution": "540x960",
    "type": "Color TN-TFT LCD display",
    "ppi": 245
  },
  "cameras": [],
  "battery_mah": 2100,
  "charging_wired_w": null,
  "charging_wireless_w": null,
  "weight_g": 137.8,
  "dimensions": {},
  "ip_rating": null,
  "os": "Android",
  "os_version": null,
  "connectivity": {},
  "image_url": null,
  "images": [],
  "score": {
    "algorithm_version": "2.0.0",
    "overall": 20.5,
    "performance": null,
    "camera": null,
    "battery": 6.0,
    "display": 35.0,
    "value": null,
    "perf": {
      "index": null,
      "percentile": null,
      "tier": null,
      "era": "2014-2016",
      "source": null
    }
  },
  "verified": false,
  "source_urls": [
    "https://phonedb.net/index.php?m=device&id=6106"
  ],
  "created_at": "2026-06-24T08:54:14.568758",
  "updated_at": "2026-06-24T08:54:14.568771"
}
