{
  "id": 139,
  "slug": "arc-a770",
  "name": "Arc A770",
  "manufacturer": {
    "slug": "intel",
    "name": "Intel",
    "url": "/v1/brands/intel"
  },
  "architecture": "Alchemist",
  "release_date": "2022-10-12",
  "msrp_usd": 349,
  "cuda_cores": null,
  "stream_processors": 4096,
  "rt_cores": 32,
  "tensor_cores": null,
  "memory_gb": 16.0,
  "memory_type": "GDDR6",
  "memory_bus_bit": 256,
  "memory_bandwidth_gbps": 560.0,
  "base_clock_mhz": 2100,
  "boost_clock_mhz": 2400,
  "tdp_w": 225,
  "pcie_version": "PCIe 4.0",
  "fp32_tflops": 19.66,
  "blender_score": 2448.23,
  "verified": false,
  "source_urls": [
    "https://www.intel.com/content/www/us/en/products/sku/229151/intel-arc-a770-graphics-16gb/specifications.html",
    "https://www.techpowerup.com/gpu-specs/intel-arc-a770.c3849",
    "https://opendata.blender.org/snapshots/opendata-latest.zip",
    "https://www.topcpu.net/en/gpu-r/3dmark-time-spy",
    "https://www.videocardbenchmark.net/gpu_list.php",
    "https://www.topcpu.net/en/gpu-r/"
  ],
  "url": "/v1/gpus/arc-a770"
}
