{
  "slug": "lg-k130-k-series-k4-dual-sim-lte",
  "name": "LG K130 K Series K4 Dual SIM LTE",
  "brand": "lg",
  "soc": "mediatek-mt6735m",
  "release_date": "2016-02-02",
  "ram_gb": 1,
  "battery_mah": 1940,
  "weight_g": 120.0,
  "os": "Android",
  "verified": true,
  "source_urls": [
    "https://phonedb.net/index.php?m=device&id=9713"
  ],
  "storage_options_gb": [
    8
  ],
  "display": {
    "size_inch": 4.49,
    "resolution": "480x854",
    "type": "Color IPS TFT LCD display",
    "ppi": 218
  },
  "market_regions": "Eastern Europe , Europe , Western Europe",
  "market_countries": "Czech , Hungary , Portugal , Romania , Slovakia , Spain"
}
