{
  "slug": "fujitsu-smartphone-arrows-m01-4g-lte",
  "name": "Fujitsu Smartphone ARROWS M01 4G LTE",
  "brand": "fujitsu",
  "soc": "qualcomm-snapdragon-400-msm8926",
  "release_date": "2015-03-11",
  "ram_gb": 1,
  "battery_mah": 2500,
  "weight_g": 153.0,
  "os": "Android",
  "verified": true,
  "source_urls": [
    "https://phonedb.net/index.php?m=device&id=7727"
  ],
  "storage_options_gb": [
    8
  ],
  "display": {
    "size_inch": 4.5,
    "resolution": "720x1280",
    "type": "AM-OLED display",
    "ppi": 326
  },
  "market_regions": "Asia",
  "market_countries": "Japan"
}
