{
  "id": 87290,
  "slug": "zte-grand-xmax-aitoolbuzz-13560-1gb-8gb-3g",
  "base_model_slug": "grand-xmax",
  "name": "ZTE Grand Xmax",
  "brand": {
    "id": 55,
    "slug": "zte",
    "name": "ZTE",
    "country": "CN",
    "url": "/v1/brands/zte"
  },
  "soc": {
    "id": 1568,
    "slug": "qualcomm-snapdragon-200",
    "name": "Qualcomm Snapdragon 200",
    "manufacturer": {
      "slug": "qualcomm",
      "name": "Qualcomm",
      "url": "/v1/brands/qualcomm"
    },
    "process_nm": 28.0,
    "gpu_name": "Adreno 302",
    "url": "/v1/socs/qualcomm-snapdragon-200"
  },
  "release_date": "2014-10-01",
  "msrp_usd": null,
  "ram_gb": 1,
  "storage_options_gb": [
    8
  ],
  "variant": {
    "region": "global",
    "source_dataset": "devadigax/awesome-mobiles-database-by-aitoolbuzz-com",
    "source_key": "devadigax/awesome-mobiles-database-by-aitoolbuzz-com:13560",
    "memory": {
      "ram_gb": 1,
      "storage_gb": 8
    },
    "network": {
      "cellular": "3G"
    },
    "sim": "Micro-SIM"
  },
  "display": {
    "size_inch": 6.0,
    "resolution": "720x1280 pixels",
    "type": "TFT"
  },
  "cameras": [
    {
      "type": "main",
      "raw": "8MP"
    },
    {
      "type": "selfie",
      "raw": "1 MP"
    }
  ],
  "battery_mah": 3200,
  "charging_wired_w": null,
  "charging_wireless_w": null,
  "weight_g": 171.8,
  "dimensions": {},
  "ip_rating": null,
  "os": "Android 4.4.2",
  "os_version": null,
  "connectivity": {},
  "image_url": "https://aitoolbuzz.com/assets/agents/mobiles/zte-grand-xmax.jpg",
  "images": [],
  "score": {
    "algorithm_version": "2.0.0",
    "overall": 17.0,
    "performance": null,
    "camera": null,
    "battery": 17.0,
    "display": null,
    "value": null,
    "perf": {
      "index": null,
      "percentile": null,
      "tier": null,
      "era": "2014-2016",
      "source": null
    }
  },
  "verified": false,
  "source_urls": [
    "https://aitoolbuzz.com/mobiles/zte-grand-xmax"
  ],
  "created_at": "2026-06-24T08:54:26.627047",
  "updated_at": "2026-06-24T08:54:26.627059"
}
