{
  "id": 3238,
  "slug": "intel-celeron-n3060-1-60ghz",
  "name": "Intel Celeron N3060 @ 1.60GHz",
  "manufacturer": {
    "slug": "intel",
    "name": "Intel",
    "url": "/v1/brands/intel"
  },
  "release_date": "2016-04-01",
  "segment": "laptop",
  "architecture": "Unknown",
  "socket": null,
  "process_node": null,
  "cores": 2,
  "threads": 2,
  "p_cores": null,
  "e_cores": null,
  "base_clock_ghz": 1.6,
  "boost_clock_ghz": 2.48,
  "l3_cache_mb": null,
  "tdp_w": 6,
  "max_tdp_w": null,
  "integrated_graphics": null,
  "memory_support": null,
  "msrp_usd": 282,
  "verified": false,
  "source_urls": [
    "https://www.kaggle.com/datasets/lincolnzh/cpu-specifications-dataset"
  ],
  "created_at": "2026-06-17T05:47:51.987069",
  "updated_at": "2026-06-17T05:47:51.987069",
  "url": "/v1/cpus/intel-celeron-n3060-1-60ghz"
}
