{
  "id": 74141,
  "slug": "vivo-x6s-plus-beridzeg45-3336-4gb",
  "base_model_slug": "x6s-plus",
  "name": "vivo X6S Plus",
  "brand": {
    "id": 52,
    "slug": "vivo",
    "name": "vivo",
    "country": "CN",
    "url": "/v1/brands/vivo"
  },
  "soc": {
    "id": 1596,
    "slug": "qualcomm-msm8976-snapdragon-652",
    "name": "Qualcomm MSM8976 Snapdragon 652",
    "manufacturer": {
      "slug": "qualcomm",
      "name": "Qualcomm",
      "url": "/v1/brands/qualcomm"
    },
    "process_nm": 28.0,
    "gpu_name": "Adreno 510",
    "url": "/v1/socs/qualcomm-msm8976-snapdragon-652"
  },
  "release_date": "2016-01-01",
  "msrp_usd": null,
  "ram_gb": 4,
  "storage_options_gb": [],
  "variant": {
    "region": "global",
    "source_dataset": "beridzeg45/gsmarena-smartphones",
    "source_key": "beridzeg45/gsmarena-smartphones:3336"
  },
  "display": {
    "size_inch": 5.7,
    "resolution": "1080x1920",
    "type": "Super AMOLED"
  },
  "cameras": [
    {
      "type": "main",
      "mp": 16.0
    },
    {
      "type": "selfie",
      "mp": 8.0
    }
  ],
  "battery_mah": 3000,
  "charging_wired_w": null,
  "charging_wireless_w": null,
  "weight_g": 172.5,
  "dimensions": {},
  "ip_rating": null,
  "os": "Android",
  "os_version": null,
  "connectivity": {},
  "image_url": null,
  "images": [],
  "score": {
    "algorithm_version": "2.0.0",
    "overall": 11.2,
    "performance": null,
    "camera": 7.5,
    "battery": 15.0,
    "display": null,
    "value": null,
    "perf": {
      "index": null,
      "percentile": null,
      "tier": null,
      "era": "2014-2016",
      "source": null
    }
  },
  "verified": false,
  "source_urls": [
    "https://www.gsmarena.com/vivo_x6s_plus-8020.php"
  ],
  "created_at": "2026-06-24T08:54:21.685556",
  "updated_at": "2026-06-24T08:54:21.685570"
}
