{
  "slug": "bbk-vivo-v23-pro-5g-premium-edition-dual-sim-td-lte-in-256gb-v2132-bbk-v2132",
  "name": "BBK Vivo V23 Pro 5G Premium Edition Dual SIM TD-LTE IN 256GB V2132 (BBK V2132)",
  "brand": "vivo",
  "soc": "mediatek-dimensity-1200-mt6893",
  "release_date": "2022-01-01",
  "ram_gb": 12,
  "battery_mah": 4300,
  "weight_g": 171.0,
  "os": "Android",
  "verified": false,
  "source_urls": [
    "https://phonedb.net/index.php?m=device&id=20166"
  ],
  "storage_options_gb": [
    256
  ],
  "display": {
    "size_inch": 6.56,
    "resolution": "1080x2376",
    "type": "AM-OLED display",
    "ppi": 398
  },
  "market_regions": "Asia",
  "market_countries": "India"
}
