{
  "slug": "radeon-hd-8970m",
  "name": "Radeon HD 8970M",
  "manufacturer": "amd",
  "architecture": "GCN 1.0",
  "release_date": "2013-05-14",
  "cuda_cores": 1280,
  "stream_processors": 1280,
  "memory_gb": 4.0,
  "memory_type": "GDDR5",
  "memory_bus_bit": 256,
  "memory_bandwidth_gbps": 153.6,
  "base_clock_mhz": 850,
  "boost_clock_mhz": 900,
  "tdp_w": 100,
  "pcie_version": "PCIe 3.0 x16",
  "fp32_tflops": 2.304,
  "verified": false,
  "source_urls": [
    "https://www.kaggle.com/datasets/ellimaaac/gpus-specs-from-1986-to-2026"
  ]
}
