{
  "id": 20023,
  "slug": "huawei-honor-x5-4g-global-dual-sim-lte-32gb-vna-lx2-vna-l22-huawei-vanessa",
  "name": "Huawei Honor X5 4G Global Dual SIM LTE 32GB VNA-LX2 / VNA-L22 (Huawei Vanessa)",
  "brand": {
    "id": 25,
    "slug": "huawei",
    "name": "Huawei",
    "country": "CN",
    "url": "/v1/brands/huawei"
  },
  "soc": {
    "id": 1765,
    "slug": "mediatek-helio-g25-mt6762g",
    "name": "MediaTek Helio G25 MT6762G",
    "manufacturer": {
      "slug": "mediatek",
      "name": "MediaTek",
      "url": "/v1/brands/mediatek"
    },
    "process_nm": 12.0,
    "gpu_name": "IMG PowerVR GE8320",
    "url": "/v1/socs/mediatek-helio-g25-mt6762g"
  },
  "release_date": "2023-01-01",
  "msrp_usd": null,
  "ram_gb": 2,
  "storage_options_gb": [
    32
  ],
  "display": {
    "size_inch": 6.5,
    "resolution": "720x1600",
    "type": "Color IPS TFT LCD display",
    "ppi": 270
  },
  "cameras": [],
  "battery_mah": 5000,
  "charging_wired_w": null,
  "charging_wireless_w": null,
  "weight_g": 193.0,
  "dimensions": {},
  "ip_rating": null,
  "os": "Android",
  "os_version": null,
  "connectivity": {},
  "image_url": null,
  "images": [],
  "score": {
    "algorithm_version": "1.0.0",
    "overall": 32.5,
    "performance": null,
    "camera": null,
    "battery": 30.0,
    "display": 35.0,
    "value": null
  },
  "verified": false,
  "source_urls": [
    "https://phonedb.net/index.php?m=device&id=22103"
  ],
  "created_at": "2026-06-19T09:44:28.582476",
  "updated_at": "2026-06-19T09:44:28.582476"
}
