{
  "slug": "apple-iphone-13-pro-aitoolbuzz-799-6gb-128gb-5g",
  "base_model_slug": "iphone-13-pro",
  "name": "Apple iPhone 13 Pro",
  "brand": "apple",
  "release_date": "2021-09-01",
  "ram_gb": 6,
  "battery_mah": 3095,
  "weight_g": 204.0,
  "os": "iOS 15, up to iOS 18.4",
  "verified": false,
  "source_urls": [
    "https://aitoolbuzz.com/mobiles/apple-iphone-13-pro"
  ],
  "variant": {
    "region": "global",
    "source_dataset": "devadigax/awesome-mobiles-database-by-aitoolbuzz-com",
    "source_key": "devadigax/awesome-mobiles-database-by-aitoolbuzz-com:799",
    "memory": {
      "ram_gb": 6,
      "storage_gb": 128
    },
    "network": {
      "cellular": "5G"
    },
    "model_numbers": [
      "A2638",
      "A2483",
      "A2636",
      "A2639",
      "A2640",
      "iPhone14",
      "2"
    ],
    "sim": "Nano-SIM + eSIMNano-SIM + Nano-SIM"
  },
  "soc": "apple-a15-bionic",
  "storage_options_gb": [
    128,
    256,
    512,
    1024
  ],
  "display": {
    "size_inch": 6.1,
    "resolution": "1170x2532 pixels",
    "type": "Super Retina XDR OLED, 120Hz, HDR10, Dolby Vision, 1000 nits (HBM), 1200 nits (peak)"
  },
  "cameras": [
    {
      "type": "main",
      "raw": "12MP"
    },
    {
      "type": "selfie",
      "raw": "12 MP, f/2.2, 23mm (wide), 1/3.6\", 1.0µm SL 3D, (depth/biometrics sensor)"
    }
  ],
  "image_url": "https://aitoolbuzz.com/assets/agents/mobiles/apple-iphone-13-pro.jpg"
}
