{
  "slug": "tecno-pova-aitoolbuzz-11343-6gb-64gb-4g-lte",
  "base_model_slug": "pova",
  "name": "Tecno Pova",
  "brand": "tecno",
  "release_date": "2020-10-01",
  "ram_gb": 6,
  "battery_mah": 6000,
  "weight_g": 150.0,
  "os": "Android 10, HIOS 7.0",
  "verified": false,
  "source_urls": [
    "https://aitoolbuzz.com/mobiles/tecno-pova"
  ],
  "variant": {
    "region": "global",
    "source_dataset": "devadigax/awesome-mobiles-database-by-aitoolbuzz-com",
    "source_key": "devadigax/awesome-mobiles-database-by-aitoolbuzz-com:11343",
    "memory": {
      "ram_gb": 6,
      "storage_gb": 64
    },
    "network": {
      "cellular": "4G LTE"
    },
    "model_numbers": [
      "LD7",
      "LD7j",
      "MZ-TECNO LD7"
    ],
    "sim": "Nano-SIM + Nano-SIM"
  },
  "soc": "mediatek-helio-g70-mt6769v-cb",
  "storage_options_gb": [
    64,
    128
  ],
  "display": {
    "size_inch": 6.8,
    "resolution": "720x1640 pixels",
    "type": "IPS LCD, 480 nits (peak)"
  },
  "cameras": [
    {
      "type": "main",
      "raw": "16MP"
    },
    {
      "type": "selfie",
      "raw": "8 MP, f/2.0"
    }
  ],
  "image_url": "https://aitoolbuzz.com/assets/agents/mobiles/tecno-pova.jpg"
}
