{
  "slug": "qmobile-noir-lt150-beridzeg45-913-1gb",
  "base_model_slug": "noir-lt150",
  "name": "QMobile Noir LT150",
  "brand": "qmobile",
  "release_date": "2015-01-01",
  "ram_gb": 1,
  "battery_mah": 1800,
  "weight_g": 150.0,
  "os": "Android",
  "verified": false,
  "source_urls": [
    "https://www.gsmarena.com/qmobile_noir_lt150-7337.php"
  ],
  "variant": {
    "region": "global",
    "source_dataset": "beridzeg45/gsmarena-smartphones",
    "source_key": "beridzeg45/gsmarena-smartphones:913"
  },
  "soc": "mediatek-mt6590",
  "display": {
    "size_inch": 4.7,
    "resolution": "480x854",
    "type": "TFT"
  },
  "cameras": [
    {
      "type": "main",
      "mp": 5.0
    },
    {
      "type": "selfie",
      "mp": 2.0
    }
  ]
}
