{
  "slug": "zte-blade-v40s-beridzeg45-4476-6gb",
  "base_model_slug": "blade-v40s",
  "name": "ZTE Blade V40s",
  "brand": "zte",
  "release_date": "2022-09-30",
  "ram_gb": 6,
  "battery_mah": 4500,
  "weight_g": 184.0,
  "os": "Android v12",
  "verified": false,
  "source_urls": [
    "https://www.gsmarena.com/zte_blade_v40s-11917.php"
  ],
  "variant": {
    "region": "global",
    "source_dataset": "beridzeg45/gsmarena-smartphones",
    "source_key": "beridzeg45/gsmarena-smartphones:4476"
  },
  "soc": "unisoc-tiger-t618",
  "display": {
    "size_inch": 6.67,
    "resolution": "1080x2400",
    "type": "AMOLED"
  },
  "cameras": [
    {
      "type": "selfie",
      "mp": 8.0
    }
  ]
}
