{
  "slug": "samsung-z630-allphones-7104-1gb-3g",
  "base_model_slug": "z630",
  "name": "Samsung Z630",
  "brand": "samsung",
  "release_date": "2007-01-01",
  "ram_gb": 1,
  "battery_mah": 800,
  "weight_g": 95.0,
  "os": "Feature phone",
  "verified": false,
  "source_urls": [
    "https://www.kaggle.com/datasets/madajaswanth/phone-dataset-8461-phones"
  ],
  "variant": {
    "region": "global",
    "source_dataset": "madajaswanth/phone-dataset-8461-phones",
    "source_key": "madajaswanth/phone-dataset-8461-phones:7104",
    "network": {
      "cellular": "3G"
    },
    "sim": "Mini-SIM"
  },
  "soc": "samsung-mobile-platform-2007",
  "display": {
    "resolution": "240 x 320 pixels, 4:3 ratio (~182 ppi density)"
  },
  "cameras": [
    {
      "type": "main",
      "raw": "2 MP"
    },
    {
      "type": "selfie",
      "raw": "VGA videocall camera"
    }
  ]
}
