{
  "id": 1375,
  "slug": "hot-12i",
  "name": "Hot 12i",
  "brand": {
    "id": 19,
    "slug": "infinix",
    "name": "Infinix Mobile",
    "country": "CN",
    "url": "/v1/brands/infinix"
  },
  "soc": {
    "id": 41,
    "slug": "helio-a22",
    "name": "Helio A22",
    "manufacturer": {
      "slug": "mediatek",
      "name": "MediaTek",
      "url": "/v1/brands/mediatek"
    },
    "process_nm": 12.0,
    "gpu_name": "IMG PowerVR GE8300",
    "url": "/v1/socs/helio-a22"
  },
  "release_date": "2022-01-01",
  "msrp_usd": 139,
  "ram_gb": 4,
  "storage_options_gb": [
    64
  ],
  "display": {
    "size_inch": 6.6
  },
  "cameras": [
    {
      "type": "main",
      "mp": 13.0
    },
    {
      "type": "selfie",
      "mp": 8.0
    }
  ],
  "battery_mah": 5000,
  "charging_wired_w": null,
  "charging_wireless_w": null,
  "weight_g": 190.0,
  "dimensions": {},
  "ip_rating": null,
  "os": "Android",
  "os_version": null,
  "connectivity": {},
  "image_url": null,
  "images": [],
  "score": {
    "algorithm_version": "1.0.0",
    "overall": 17.6,
    "performance": null,
    "camera": 5.3,
    "battery": 30.0,
    "display": null,
    "value": 58.8
  },
  "verified": false,
  "source_urls": [
    "https://www.kaggle.com/datasets/abdulmalik1518/mobiles-dataset-2025"
  ],
  "created_at": "2026-06-19T00:43:44.324605",
  "updated_at": "2026-06-19T00:43:44.324605"
}
