{
  "slug": "sony-ericsson-g700-aitoolbuzz-10873-1gb-3g",
  "base_model_slug": "g700",
  "name": "Sony Ericsson G700",
  "brand": "sony-ericsson",
  "release_date": "2008-02-01",
  "ram_gb": 1,
  "battery_mah": 950,
  "weight_g": 99.0,
  "os": "Symbian, UIQ",
  "verified": false,
  "source_urls": [
    "https://aitoolbuzz.com/mobiles/sony-ericsson-g700"
  ],
  "variant": {
    "region": "global",
    "source_dataset": "devadigax/awesome-mobiles-database-by-aitoolbuzz-com",
    "source_key": "devadigax/awesome-mobiles-database-by-aitoolbuzz-com:10873",
    "network": {
      "cellular": "3G"
    },
    "sim": "Mini-SIM"
  },
  "soc": "n-a",
  "display": {
    "size_inch": 2.4,
    "resolution": "240x320 pixels",
    "type": "TFT resistive touchscreen, 256K colors"
  },
  "cameras": [
    {
      "type": "main",
      "raw": "3MP"
    },
    {
      "type": "selfie",
      "raw": "Videocall camera"
    }
  ],
  "image_url": "https://aitoolbuzz.com/assets/agents/mobiles/sony-ericsson-g700.jpg"
}
