{
  "slug": "find-x5-5g-premium-edition-dual-sim-td-lte-cn-256gb-pffm10",
  "name": "Find X5 5G Premium Edition Dual SIM TD-LTE CN 256GB PFFM10",
  "brand": "oppo",
  "soc": "qualcomm-snapdragon-888-5g-sm8350",
  "release_date": "2022-02-01",
  "ram_gb": 12,
  "battery_mah": 4800,
  "weight_g": 196.0,
  "os": "Android",
  "verified": false,
  "source_urls": [
    "https://www.kaggle.com/datasets/sady36/mobile-phones-specs"
  ],
  "storage_options_gb": [
    256
  ],
  "display": {
    "size_inch": 6.55,
    "resolution": "1080x2400",
    "type": "AM-OLED display",
    "ppi": 402
  },
  "cameras": [
    {
      "type": "main",
      "mp": 50.3
    },
    {
      "type": "selfie",
      "mp": 32.0
    }
  ],
  "connectivity": {
    "bluetooth": "Bluetooth 5.2",
    "usb": "USB C reversible"
  },
  "market_countries": "China",
  "market_regions": "Asia",
  "base_model_slug": "find-x5",
  "variant": {
    "region": "us",
    "source_category": "smartphone-variant-import",
    "source_slug": "find-x5-5g-premium-edition-dual-sim-td-lte-cn-256gb-pffm10",
    "memory": {
      "ram_gb": 12,
      "storage_gb": 256
    },
    "network": {
      "cellular": "5G"
    },
    "sim": "dual SIM",
    "model_numbers": [
      "PFFM10"
    ]
  }
}
