{
  "slug": "micromax-x234-plus-aitoolbuzz-5847-1gb-2g",
  "base_model_slug": "x234-plus",
  "name": "Micromax X234+",
  "brand": "micromax",
  "release_date": "2012-06-01",
  "ram_gb": 1,
  "battery_mah": 800,
  "weight_g": 150.0,
  "os": "Feature phone",
  "verified": false,
  "source_urls": [
    "https://aitoolbuzz.com/mobiles/micromax-x234-plus"
  ],
  "variant": {
    "region": "global",
    "source_dataset": "devadigax/awesome-mobiles-database-by-aitoolbuzz-com",
    "source_key": "devadigax/awesome-mobiles-database-by-aitoolbuzz-com:5847",
    "network": {
      "cellular": "2G"
    },
    "sim": "Dual SIM (Mini-SIM)"
  },
  "soc": "micromax-mobile-platform-2012",
  "display": {
    "size_inch": 2.0,
    "resolution": "176x220 pixels",
    "type": "TFT"
  },
  "cameras": [
    {
      "type": "main",
      "raw": "0.3MP"
    }
  ],
  "image_url": "https://aitoolbuzz.com/assets/agents/mobiles/micromax-x234-plus-cff318b5.jpg"
}
