{
  "id": 13542,
  "slug": "mi-425-stellar",
  "name": "Mi-425 Stellar",
  "brand": {
    "id": 94,
    "slug": "spice",
    "name": "Spice",
    "country": "IN",
    "url": "/v1/brands/spice"
  },
  "soc": {
    "id": 542,
    "slug": "1-0-ghz",
    "name": "1.0 GHz",
    "manufacturer": {
      "slug": "arm",
      "name": "Arm",
      "url": "/v1/brands/arm"
    },
    "process_nm": 28.0,
    "gpu_name": "Unknown mobile GPU",
    "url": "/v1/socs/1-0-ghz"
  },
  "release_date": "2012-01-01",
  "msrp_usd": null,
  "ram_gb": 1,
  "storage_options_gb": [],
  "display": {
    "size_inch": 4.0,
    "resolution": "480x800",
    "type": "TFT capacitive touchscreen, 256K colors"
  },
  "cameras": [
    {
      "type": "main",
      "mp": 5.0
    }
  ],
  "battery_mah": 2000,
  "charging_wired_w": null,
  "charging_wireless_w": null,
  "weight_g": 110.0,
  "dimensions": {},
  "ip_rating": null,
  "os": "Android",
  "os_version": null,
  "connectivity": {
    "wifi": "Wi-Fi 802.11 b/g, hotspot",
    "bluetooth": "Yes",
    "usb": "Proprietary"
  },
  "image_url": null,
  "images": [],
  "score": {
    "algorithm_version": "1.0.0",
    "overall": 2.5,
    "performance": null,
    "camera": 5.0,
    "battery": 0.0,
    "display": null,
    "value": null
  },
  "verified": false,
  "source_urls": [
    "https://www.kaggle.com/datasets/msainani/gsmarena-mobile-devices"
  ],
  "created_at": "2026-06-19T02:27:16.145603",
  "updated_at": "2026-06-19T02:27:16.145603"
}
