{
  "slug": "blackview-bv9600-pro-global-dual-sim-sady36-bulgaria-6gb-128gb",
  "base_model_slug": "bv9600-pro-global-dual-sim",
  "name": "BV9600 Pro Global Dual SIM TD-LTE",
  "brand": "blackview",
  "release_date": "2018-10-01",
  "ram_gb": 6,
  "battery_mah": 5580,
  "weight_g": 268.0,
  "os": "Google Android 8.1 (Oreo)",
  "verified": false,
  "source_urls": [
    "https://www.kaggle.com/datasets/sady36/mobile-phones-specs"
  ],
  "variant": {
    "region": "bulgaria",
    "market_country": "Bulgaria",
    "source_dataset": "sady36/mobile-phones-specs",
    "source_key": "sady36/mobile-phones-specs:2159:bulgaria",
    "memory": {
      "ram_gb": 6,
      "storage_gb": 128
    },
    "market_regions": "Africa , Asia , Europe , Middle East , Oceania , Western Europe"
  },
  "soc": "mediatek-helio-p70-mt6771wt",
  "storage_options_gb": [
    128
  ],
  "display": {
    "size_inch": 6.21,
    "resolution": "1080x2248",
    "type": "AM-OLED display"
  },
  "cameras": [
    {
      "type": "main",
      "mp": 16.2
    },
    {
      "type": "selfie",
      "mp": 8.0
    }
  ],
  "connectivity": {
    "bluetooth": "Bluetooth 4.2"
  }
}
