{
  "slug": "hp-slate7-voicetab-beridzeg45-5664-1gb",
  "base_model_slug": "slate7-voicetab",
  "name": "HP Slate7 VoiceTab",
  "brand": "hp",
  "release_date": "2014-01-01",
  "ram_gb": 1,
  "battery_mah": 4100,
  "weight_g": 325.0,
  "os": "Android",
  "verified": false,
  "source_urls": [
    "https://www.gsmarena.com/hp_slate7_voicetab-5971.php"
  ],
  "variant": {
    "region": "global",
    "source_dataset": "beridzeg45/gsmarena-smartphones",
    "source_key": "beridzeg45/gsmarena-smartphones:5664"
  },
  "soc": "marvell-pxa1088",
  "display": {
    "size_inch": 7.0,
    "resolution": "800x1280",
    "type": "IPS LCD"
  },
  "cameras": [
    {
      "type": "main",
      "mp": 5.0
    },
    {
      "type": "selfie",
      "mp": 2.0
    }
  ]
}
