{
  "id": 1915,
  "slug": "motorola-moto-tab-g62-allphones-5135-4gb-64gb-4g-lte",
  "base_model_slug": "moto-tab-g62",
  "name": "Motorola Moto Tab G62",
  "brand": {
    "id": 169,
    "slug": "motorola",
    "name": "Motorola",
    "country": "US",
    "url": "/v1/brands/motorola"
  },
  "soc": null,
  "release_date": "2022-08-17",
  "msrp_usd": null,
  "ram_gb": 4.0,
  "storage_options_gb": [
    64
  ],
  "variant": {
    "region": "global",
    "source_dataset": "madajaswanth/phone-dataset-8461-phones",
    "source_key": "madajaswanth/phone-dataset-8461-phones:5135",
    "memory": {
      "ram_gb": 4,
      "storage_gb": 64
    },
    "network": {
      "cellular": "4G LTE"
    },
    "sim": "Nano-SIM (cellular model only)"
  },
  "display": {
    "resolution": "1200 x 2000 pixels, 5:3 ratio (~220 ppi density)"
  },
  "cameras": [
    {
      "type": "main",
      "raw": "8 MP, f/2.2, 118˚ (ultrawide), 1/4.0, 1.12µm, AF"
    },
    {
      "type": "selfie",
      "raw": "8 MP, (wide)"
    }
  ],
  "battery_mah": 7700,
  "charging_wired_w": null,
  "charging_wireless_w": null,
  "weight_g": 465.0,
  "dimensions": {},
  "ip_rating": null,
  "os": "Android 12, upgradable to Android 13",
  "os_version": null,
  "connectivity": {},
  "image_url": null,
  "images": [],
  "verified": false,
  "source_urls": [
    "https://www.kaggle.com/datasets/madajaswanth/phone-dataset-8461-phones"
  ],
  "created_at": "2026-06-20T19:05:44.059806",
  "updated_at": "2026-06-20T19:05:44.059806",
  "url": "/v1/tablets/motorola-moto-tab-g62-allphones-5135-4gb-64gb-4g-lte"
}
