{
  "slug": "zte-z963vl-max-duo-sady36-usa-2gb-16gb",
  "base_model_slug": "z963vl-max-duo",
  "name": "Z963VL Max Duo LTE",
  "brand": "zte",
  "release_date": "2016-09-01",
  "ram_gb": 2,
  "battery_mah": 3500,
  "weight_g": 185.0,
  "os": "Google Android 5.1 (Lollipop)",
  "verified": false,
  "source_urls": [
    "https://www.kaggle.com/datasets/sady36/mobile-phones-specs"
  ],
  "variant": {
    "region": "usa",
    "market_country": "USA",
    "source_dataset": "sady36/mobile-phones-specs",
    "source_key": "sady36/mobile-phones-specs:290:usa",
    "memory": {
      "ram_gb": 2,
      "storage_gb": 16
    },
    "market_regions": "North America"
  },
  "soc": "qualcomm-snapdragon-617-msm8952",
  "storage_options_gb": [
    16
  ],
  "display": {
    "size_inch": 6.0,
    "resolution": "1080x1920",
    "type": "Color TN-TFT LCD display"
  },
  "cameras": [
    {
      "type": "main",
      "mp": 12.6
    },
    {
      "type": "selfie",
      "mp": 4.9
    }
  ],
  "connectivity": {
    "bluetooth": "Bluetooth 4.1"
  }
}
