{
  "slug": "samsung-galaxy-note-20-ultra-4g-8gb-256gb-4g-lte",
  "name": "Samsung Galaxy Note 20 Ultra 4G",
  "brand": "samsung",
  "release_date": "2020-08-05",
  "ram_gb": 8,
  "battery_mah": 4500,
  "weight_g": 208.0,
  "os": "Android v10, upgradable to v11",
  "verified": false,
  "source_urls": [
    "https://www.kaggle.com/datasets/mayankkumarpoddar/smartprix-mobiles-dataset"
  ],
  "base_model_slug": "galaxy-note-20-ultra-4g",
  "variant": {
    "region": "global",
    "source_dataset": "mayankkumarpoddar/smartprix-mobiles-dataset",
    "memory": {
      "ram_gb": 8,
      "storage_gb": 256
    },
    "network": {
      "cellular": "4G LTE"
    }
  },
  "storage_options_gb": [
    256
  ],
  "display": {
    "size": "6.9 inches, 1440 x 3088 pixels, 120 Hz",
    "resolution": "~ 494 PPI",
    "type": "Color Dynamic AMOLED 2X (16M Colors)"
  },
  "connectivity": {
    "wifi": "Yes, with wifi-hotspot",
    "bluetooth": "Yes, v5.0, A2DP, LE, aptX",
    "nfc": "Yes",
    "usb": "Yes, USB-C v3.2"
  },
  "raw_smartprix": {
    "Battery.Bypass Charging": "",
    "Battery.Fast Charging": "Yes, 25W Fast Charging",
    "Battery.Music Playback Time": "",
    "Battery.Reverse Charging": "Yes",
    "Battery.Reverse Wireless Charging": "",
    "Battery.Size": "4500 mAh, Li-ion Battery",
    "Battery.StandBy Time": "",
    "Battery.Talk Time": "",
    "Battery.Type": "Non-Removable Battery",
    "Battery.Video Playback Time": "",
    "Battery.Wireless Charging": "Yes",
    "Brand": "Samsung",
    "Camera.Auto Focus": "Yes",
    "Camera.Camera Sensor": "",
    "Camera.Features": "Auto-HDR, Panorama",
    "Camera.Flash": "Yes, LED",
    "Camera.Front Camera": "10 MP ƒ/2.2 (Wide Angle)<br><span class=\"dim\">Punch Hole</span>",
    "Camera.Front Video Recording": "4K @ 30 fps UHD, 1080p @ 30 fps FHD",
    "Camera.OIS": "Yes",
    "Camera.Rear Camera": "108 MP ƒ/1.8 (Wide Angle)<br class=\"l\">12 MP ƒ/3 (Telephoto)<br><span class=\"dim\">Periscope Telephoto</span><br class=\"l\">12 MP ƒ/2.2 (Ultra Wide)",
    "Camera.Video Recording": "8K @ 24 fps UHD, 4K @ 30 fps UHD, 1080p @ 30 fps FHD, 720p @ 960 fps HD",
    "Connectivity.3G": "Yes",
    "Connectivity.4G": "Yes",
    "Connectivity.5G": "No",
    "Connectivity.5G Bands": "",
    "Connectivity.Bluetooth": "Yes, v5.0, A2DP, LE, aptX",
    "Connectivity.EDGE": "Yes",
    "Connectivity.GPRS": "Yes",
    "Connectivity.IR Blaster": "",
    "Connectivity.USB": "Yes, USB-C v3.2",
    "Connectivity.USB Features": "USB on-the-go, USB Charging",
    "Connectivity.Ultra Wideband (UWB) Support": "",
    "Connectivity.Vo5G": "",
    "Connectivity.VoLTE": "Yes, Dual Stand-By",
    "Connectivity.Wifi": "Yes, with wifi-hotspot",
    "Connectivity.Wifi Version": "",
    "Design.Bezel less": "",
    "Design.Colors": "",
    "Design.Design Type": "",
    "Design.Dimensions": "77.2 x 164.8 x 8.1 mm",
    "Design.Qwerty": "",
    "Design.Weight": "208 g",
    "Display.Adaptive Refresh Rate": "",
    "Display.Aspect Ratio": "19.3:9",
    "Display.Brightness": "",
    "Display.Color Gamut": "",
    "Display.Curved Display": "Yes",
    "Display.Display Dimming": "",
    "Display.Dual Display": "",
    "Display.Features": "HDR10+, Always-on display, Curved Display",
    "Display.Foldable Display": "",
    "Display.Glass Type": "Corning Gorilla Glass Victus",
    "Display.HDR Support": "",
    "Display.Notch": "Yes, Punch Hole",
    "Display.PPI": "~ 494 PPI",
    "Display.Screen to Body Ratio": "~ 92.5%",
    "Display.Size": "6.9 inches, 1440 x 3088 pixels, 120 Hz",
    "Display.Touch": "Yes",
    "Display.Type": "Color Dynamic AMOLED 2X (16M Colors)",
    "Extra.3.5mm Headphone Jack": "No",
    "Extra.AI Features": "",
    "Extra.Cooling System": "",
    "Extra.Dust Resistant": "Yes",
    "Extra.Extra": "",
    "Extra.Extra Features": "Embedded S Pen",
    "Extra.Face Unlock": "Yes",
    "Extra.Fingerprint Sensor": "Yes, In Display",
    "Extra.GPS": "Yes, with A-GPS, GLONASS, BDS, GALILEO",
    "Extra.Gaming Features": "",
    "Extra.IP Rating": "IP68",
    "Extra.NFC": "Yes",
    "Extra.Sensors": "Accelerometer, Gyro, Proximity, Compass, Barometer",
    "Extra.Splash Resistant": "",
    "Extra.Water Resistance": "Yes, 1.5 m upto 30 min",
    "General.Country of Origin": "",
    "General.Device Type": "Smartphone",
    "General.Dual Sim": "Yes",
    "General.In The Box": "",
    "General.Model": "Galaxy Note 20 Ultra",
    "General.OS Updates": "",
    "General.Release Date": "August 05, 2020",
    "General.SAR": "",
    "General.Security Updates": "",
    "General.Sim Size": "Nano SIM",
    "General.Sim Type": "Dual Sim, GSM+GSM (Hybrid Slot)",
    "General.Triple Sim": "",
    "General.eSIM Support": "",
    "Last modified": "2025-09-16",
    "Memory.Card Slot": "Yes, (Hybrid Slot), upto 1 TB",
    "Memory.Expandable RAM": "",
    "Memory.Phonebook": "",
    "Memory.RAM": "8 GB",
    "Memory.RAM Type": "",
    "Memory.Storage": "256 GB",
    "Memory.Storage Type": "",
    "Multimedia.Audio Features": "",
    "Multimedia.Audio Jack Type": "",
    "Multimedia.Document Reader": "Yes",
    "Multimedia.Email": "Yes",
    "Multimedia.FM Radio": "No",
    "Multimedia.Music": "Yes",
    "Multimedia.Speaker Type": "",
    "Multimedia.Supports": "",
    "Multimedia.Video": "Yes",
    "Name": "Samsung Galaxy Note 20 Ultra 4G",
    "Performance.3DMark Score": "",
    "Performance.AnTuTu Score": "",
    "Performance.AnTuTu Storage Score": "",
    "Performance.Battery Test Result": "",
    "Performance.Camera Score": "",
    "Performance.Geekbench Score": "",
    "Performance.Speaker Score": "",
    "Price": "99999.0",
    "Price Drop": "0.0",
    "Price Drop Amount": "0",
    "Related Items": "[{\"Name\": \"Samsung Galaxy Note 10 Plus\", \"Price\": 32999}, {\"Name\": \"Samsung Galaxy Note 20\", \"Price\": 86000}, {\"Name\": \"Samsung Galaxy S22 Ultra 5G\", \"Price\": 69998}, {\"Name\": \"Apple iPhone 16e\", \"Price\": 51499}, {\"Name\": \"Samsung Galaxy S20 Plus 5G\", \"Price\": 85990}, {\"Name\": \"Oppo F31 Pro 5G\", \"Price\": 26999}, {\"Name\": \"Vivo Y500 5G\", \"Price\": 17990}, {\"Name\": \"Oppo F31 5G\", \"Price\": 22999}, {\"Name\": \"Apple iPhone 17 Pro Max\", \"Price\": 149900}]",
    "Technical.Browser": "Yes, supports HTML5",
    "Technical.CPU": "2.73 GHz, Octa Core Processor",
    "Technical.Chipset": "Samsung Exynos 990",
    "Technical.Core Details": "2x2.73 GHz Mongoose M5 & 2x2.60 GHz Cortex-A76 & 4x2.0 GHz Cortex-A55",
    "Technical.Custom UI": "",
    "Technical.Fabrication Node": "",
    "Technical.GPU": "Mali-G77 MP11",
    "Technical.Java": "No",
    "Technical.NPU": "",
    "Technical.OS": "Android v10, upgradable to v11"
  },
  "soc": "exynos-990"
}
