{
  "slug": "apple-watch-series-1-aluminum-42mm-aitoolbuzz-853-0-5gb-8gb-2g",
  "base_model_slug": "watch-series-1-aluminum-42mm",
  "name": "Apple Watch Series 1 Aluminum 42mm",
  "brand": "apple",
  "release_date": "2016-09-01",
  "ram_gb": 0.5,
  "battery_mah": 250,
  "weight_g": 30.0,
  "os": "watchOS 3.0, up to watchOS 6.2.8",
  "verified": false,
  "source_urls": [
    "https://aitoolbuzz.com/mobiles/apple-watch-series-1-aluminum-42mm"
  ],
  "variant": {
    "region": "global",
    "source_dataset": "devadigax/awesome-mobiles-database-by-aitoolbuzz-com",
    "source_key": "devadigax/awesome-mobiles-database-by-aitoolbuzz-com:853",
    "memory": {
      "ram_gb": 0.5,
      "storage_gb": 8
    },
    "network": {
      "cellular": "2G"
    },
    "model_numbers": [
      "A1803"
    ],
    "sim": "No"
  },
  "soc": "apple-s1p",
  "storage_options_gb": [
    8
  ],
  "display": {
    "size_inch": 1.65,
    "resolution": "390x312 pixels",
    "type": "Retina OLED, 450 nits (peak)"
  },
  "cameras": [
    {
      "type": "main",
      "raw": "NO"
    }
  ],
  "image_url": "https://aitoolbuzz.com/assets/agents/mobiles/apple-watch-series-1-aluminum-42mm.jpg"
}
