{
  "slug": "lg-d213-l-series-iii-l50-sporty-d213n",
  "name": "LG D213 L Series III L50 Sporty / D213N",
  "brand": "lg",
  "soc": "mediatek-mt6572",
  "release_date": "2014-06-01",
  "ram_gb": 1,
  "battery_mah": 1900,
  "weight_g": 142.0,
  "os": "Android",
  "verified": true,
  "source_urls": [
    "https://phonedb.net/index.php?m=device&id=6927"
  ],
  "storage_options_gb": [
    4
  ],
  "display": {
    "size_inch": 4.0,
    "resolution": "480x800",
    "type": "Color IPS TFT LCD display",
    "ppi": 233
  }
}
